genshinrecipes/__init__.py
genshinrecipes/data.py
genshinrecipes/recipes.json
genshinrecipes-2.6.0.dist-info/LICENSE
genshinrecipes-2.6.0.dist-info/METADATA
genshinrecipes-2.6.0.dist-info/WHEEL
genshinrecipes-2.6.0.dist-info/top_level.txt
genshinrecipes-2.6.0.dist-info/RECORD
