Metadata-Version: 2.1
Name: genshinrecipes
Version: 2.6.0
Summary: UNKNOWN
Home-page: https://github.com/tilda/genshin-recipe-data
Author: tilda
Author-email: tda@stairway.cf
License: UNKNOWN
Platform: UNKNOWN
Requires-Python: >=3.6
License-File: LICENSE
